odoo/addons/mrp_warehouse_calendar/README.rst
odoo/addons/mrp_warehouse_calendar/__init__.py
odoo/addons/mrp_warehouse_calendar/__manifest__.py
odoo/addons/mrp_warehouse_calendar/i18n/de.po
odoo/addons/mrp_warehouse_calendar/i18n/es.po
odoo/addons/mrp_warehouse_calendar/i18n/it.po
odoo/addons/mrp_warehouse_calendar/i18n/mrp_warehouse_calendar.pot
odoo/addons/mrp_warehouse_calendar/i18n/pt_BR.po
odoo/addons/mrp_warehouse_calendar/models/__init__.py
odoo/addons/mrp_warehouse_calendar/models/mrp_production.py
odoo/addons/mrp_warehouse_calendar/models/stock_rule.py
odoo/addons/mrp_warehouse_calendar/readme/CONFIGURE.md
odoo/addons/mrp_warehouse_calendar/readme/CONTRIBUTORS.md
odoo/addons/mrp_warehouse_calendar/readme/DESCRIPTION.md
odoo/addons/mrp_warehouse_calendar/readme/USAGE.md
odoo/addons/mrp_warehouse_calendar/static/description/change_day.gif
odoo/addons/mrp_warehouse_calendar/static/description/developer_mode.gif
odoo/addons/mrp_warehouse_calendar/static/description/icon.png
odoo/addons/mrp_warehouse_calendar/static/description/index.html
odoo/addons/mrp_warehouse_calendar/static/description/manufacturing_order.png
odoo/addons/mrp_warehouse_calendar/static/description/replenish.png
odoo/addons/mrp_warehouse_calendar/static/description/warehouse_management.gif
odoo/addons/mrp_warehouse_calendar/static/description/working_schedules.gif
odoo/addons/mrp_warehouse_calendar/tests/__init__.py
odoo/addons/mrp_warehouse_calendar/tests/test_mrp_warehouse_calendar.py
odoo_addon_mrp_warehouse_calendar-18.0.1.0.1.dist-info/METADATA
odoo_addon_mrp_warehouse_calendar-18.0.1.0.1.dist-info/WHEEL
odoo_addon_mrp_warehouse_calendar-18.0.1.0.1.dist-info/top_level.txt
odoo_addon_mrp_warehouse_calendar-18.0.1.0.1.dist-info/RECORD
